[
    [
        "2025-01-01",
        "ORY",
        "MUC",
        {
            "VALID": true,
            "PRICE": "120.21"
        }
    ],
    [
        "2025-01-02",
        "MUC",
        "BRU",
        {
            "VALID": true,
            "PRICE": "130.71"
        }
    ],
    [
        "2025-01-03",
        "BRU",
        "MAD",
        {
            "VALID": true,
            "PRICE": "59.38"
        }
    ],
    [
        "2025-01-02",
        "MUC",
        "MAD",
        {
            "VALID": true,
            "PRICE": "94.64"
        }
    ],
    [
        "2025-01-03",
        "MAD",
        "BRU",
        {
            "VALID": true,
            "PRICE": "54.07"
        }
    ],
    [
        "2025-01-01",
        "ORY",
        "BRU",
        {
            "VALID": true,
            "PRICE": "124.48"
        }
    ],
    [
        "2025-01-02",
        "BRU",
        "MUC",
        {
            "VALID": true,
            "PRICE": "108.20"
        }
    ],
    [
        "2025-01-03",
        "MUC",
        "MAD",
        {
            "VALID": true,
            "PRICE": "94.64"
        }
    ],
    [
        "2025-01-02",
        "BRU",
        "MAD",
        {
            "VALID": true,
            "PRICE": "72.38"
        }
    ],
    [
        "2025-01-03",
        "MAD",
        "MUC",
        {
            "VALID": true,
            "PRICE": "77.80"
        }
    ],
    [
        "2025-01-01",
        "ORY",
        "MAD",
        {
            "VALID": true,
            "PRICE": "75.39"
        }
    ],
    [
        "2025-01-02",
        "MAD",
        "MUC",
        {
            "VALID": true,
            "PRICE": "77.80"
        }
    ],
    [
        "2025-01-03",
        "MUC",
        "BRU",
        {
            "VALID": true,
            "PRICE": "123.73"
        }
    ],
    [
        "2025-01-02",
        "MAD",
        "BRU",
        {
            "VALID": true,
            "PRICE": "88.23"
        }
    ],
    [
        "2025-01-03",
        "BRU",
        "MUC",
        {
            "VALID": true,
            "PRICE": "108.20"
        }
    ],
    [
        "2025-01-03",
        "MUC",
        "ORY",
        {
            "VALID": true,
            "PRICE": "167.46"
        }
    ],
    [
        "2025-01-03",
        "BRU",
        "ORY",
        {
            "VALID": true,
            "PRICE": "126.60"
        }
    ],
    [
        "2025-01-03",
        "MAD",
        "ORY",
        {
            "VALID": true,
            "PRICE": "100.80"
        }
    ]
]